palvisualpy/__init__.py
palvisualpy/table.py
palvisualpy-0.1.1.dist-info/entry_points.txt
palvisualpy-0.1.1.dist-info/licenses/LICENSE.txt
palvisualpy-0.1.1.dist-info/WHEEL
palvisualpy-0.1.1.dist-info/METADATA
palvisualpy-0.1.1.dist-info/RECORD
